[{"model": "employees.employee", "pk": 1, "fields": {"password": "pbkdf2_sha256$100000$pcZycpDekQ7r$Rn5i+IEJUzmBSwuscZylfL9upEHkCeO6FKK4/19uO5c=", "last_login": "2018-05-31T14:34:26.209Z", "is_superuser": true, "username": "admin", "first_name": "", "last_name": "", "is_staff": true, "is_active": true, "date_joined": "2018-05-31T14:34:09.567Z", "rank": "", "department": "", "phone": null, "email": "djangotestmail4@gmail.com", "about": null, "groups": [], "user_permissions": []}}, {"model": "employees.employee", "pk": 2, "fields": {"password": "pbkdf2_sha256$100000$vVdE9Zbj0QOO$b/ZktbR/WAWLn0foc6aANcXyyZ53OXFx4Fwi6MDsWcs=", "last_login": "2018-05-31T14:35:55.557Z", "is_superuser": false, "username": "HRUser", "first_name": "", "last_name": "", "is_staff": true, "is_active": true, "date_joined": "2018-05-31T14:35:34.212Z", "rank": "J", "department": "HR", "phone": null, "email": "djangotestmail4@gmail.com", "about": null, "groups": [], "user_permissions": []}}, {"model": "employees.employee", "pk": 3, "fields": {"password": "pbkdf2_sha256$100000$bc7mOVwbYE2J$A4ZUN+xIyqQpS300POKwReVieWGy865NVwkCpDHPejk=", "last_login": "2018-05-31T14:37:24.084Z", "is_superuser": false, "username": "Buyer", "first_name": "", "last_name": "", "is_staff": false, "is_active": true, "date_joined": "2018-05-31T14:36:51.265Z", "rank": "J", "department": "BU", "phone": 123, "email": "djangotestmail4@gmail.com", "about": "It's me", "groups": [], "user_permissions": []}}]